pycurves/__init__.py
pycurves-0.0.1.dist-info/LICENSE
pycurves-0.0.1.dist-info/METADATA
pycurves-0.0.1.dist-info/WHEEL
pycurves-0.0.1.dist-info/top_level.txt
pycurves-0.0.1.dist-info/RECORD
