Metadata-Version: 2.1
Name: pycurves
Version: 0.0.1
Author-email: Shi Changshan <changshanshi@outlook.com>
License: MIT License
Project-URL: Homepage, https://github.com/Bardreamaster/pycurves
Keywords: timer
Classifier: License :: OSI Approved :: MIT License
Classifier: Programming Language :: Python :: 3
License-File: LICENSE
Requires-Dist: textual
Requires-Dist: textual-plotext
